google_account_local/__init__.py
google_account_local/google_account_local.py
google_account_local/google_account_local_constants.py
google_account_local-0.0.33.dist-info/METADATA
google_account_local-0.0.33.dist-info/WHEEL
google_account_local-0.0.33.dist-info/top_level.txt
google_account_local-0.0.33.dist-info/RECORD
