Metadata-Version: 2.4
Name: google-account-local
Version: 0.0.33
Summary: PyPI Package for Circles google-account-local Python
Home-page: https://github.com/circles-zone/google-account-local-python-package
Author: Circles
Author-email: info@circlez.ai
Classifier: Programming Language :: Python :: 3
Classifier: Operating System :: OS Independent
Requires-Dist: logger-local
Requires-Dist: database-mysql-local>=0.1.1
Requires-Dist: python-sdk-remote
Requires-Dist: google-auth-oauthlib>=1.2.0
Requires-Dist: google-auth-httplib2>=0.2.0
Requires-Dist: google-api-python-client>=2.128.0
Requires-Dist: user-external-local>=0.0.42
Requires-Dist: profile-local>=0.0.91
Dynamic: author
Dynamic: author-email
Dynamic: classifier
Dynamic: description
Dynamic: description-content-type
Dynamic: home-page
Dynamic: requires-dist
Dynamic: summary
